README.md
setup.py
promindset_tools/__init__.py
promindset_tools/fib.py
promindset_tools/palindrome.py
promindset_tools.egg-info/PKG-INFO
promindset_tools.egg-info/SOURCES.txt
promindset_tools.egg-info/dependency_links.txt
promindset_tools.egg-info/top_level.txt